Workbook

Sheet Suivi
A1: # | B1: Catégorie | C1: Organisme | D1: Région | E1: E-mail | F1: Source / fiabilité | G1: Angle | H1: Objet du mail | I1: Statut | J1: Date d'envoi | K1: Relance prévue (J+5 ouvré) | L1: Date de relance | M1: Réponse | N1: Lien obtenu (URL) | O1: Notes
A2: 1 | B2: Média | C2: Maddyness | D2: National | E2: redaction@maddyness.com | F2: Officiel (page Facebook de Maddyness) | G2: Baromètre des prix | H2: 83 % des logiciels de caisse cachent leurs prix (étude TPE 2027) | I2: Relancé | J2: 46314 | K2: =IF(J2="","",WORKDAY(J2+4,1)) -> 46321 | L2: 46321 | O2: Relancé
A3: 2 | B3: Média | C3: Le Blog du Dirigeant | D3: National | E3: contact@leblogdudirigeant.com | F3: Officiel (page contact, indexée il y a environ 3 ans) | G3: Baromètre des prix | H3: Une donnée inédite pour vos lecteurs dirigeants de TPE | I3: Répondu | J3: 46314 | K3: =IF(J3="","",WORKDAY(J3+4,1)) -> 46321 | M3: Oui | O3: 19/10 : propose un article sponsorisé (500 € HT fourni, 650 € HT rédigé). Décliné le 19/10 ; proposé un extrait de données gratuit. Pas de relance.
A4: 3 | B4: Média | C4: Compta-Online | D4: National | E4: forum@compta-online.com | F4: Fournie par toi | G4: Simulateurs | H4: Des simulateurs gratuits à intégrer pour vos lecteurs (TVA, charges, IK) | I4: Relancé | J4: 46314 | K4: =IF(J4="","",WORKDAY(J4+4,1)) -> 46321 | L4: 46321 | O4: Relancé
A5: 4 | B5: Média | C5: Portail Auto-Entrepreneur | D5: National | E5: contact@portail-autoentrepreneur.fr | F5: Fournie par toi | G5: Simulateurs charges + TVA | H5: Un simulateur de charges gratuit pour vos lecteurs auto-entrepreneurs | I5: Relancé | J5: 46314 | K5: =IF(J5="","",WORKDAY(J5+4,1)) -> 46321 | L5: 46321 | O5: Relancé
A6: 5 | B6: Média | C6: Journal du Freelance | D6: National | E6: tavor.management@gmail.com | F6: Fournie par toi | G6: Calculateur TJM | H6: Un calculateur de TJM gratuit pour vos lecteurs freelances | I6: Relancé | J6: 46314 | K6: =IF(J6="","",WORKDAY(J6+4,1)) -> 46321 | L6: 46321 | O6: Relancé
A7: 6 | B7: Expert-comptable | C7: les-experts-comptables.fr | D7: National | E7: (page Contact du site) | F7: Article cité : /ressources/facturation-electronique-auto-entrepreneur/ | G7: Simulateur seuil TVA | H7: Un simulateur de seuil de TVA gratuit pour compléter votre guide auto-entrepreneur | I7: Pas de réponse | K7: =IF(J7="","",WORKDAY(J7+4,1)) | O7: Brouillon supprimé le 19/10 (pas d’adresse publique) : passer par le formulaire du site si besoin
A8: 7 | B8: Fédération | C8: FNAE | D8: National | E8: contact@fnae.fr | F8: Fournie par toi | G8: Guide + check-list | H8: Une ressource gratuite pour vos adhérents auto-entrepreneurs | I8: Relancé | J8: 46314 | K8: =IF(J8="","",WORKDAY(J8+4,1)) -> 46321 | L8: 46321 | O8: Relancé
A9: 8 | B9: Fédération | C9: Union des auto-entrepreneurs | D9: National | E9: contact@union-auto-entrepreneurs.com | F9: Fournie par toi | G9: Guide + check-list | H9: Une ressource gratuite pour les auto-entrepreneurs que vous accompagnez | I9: Relancé | J9: 46314 | K9: =IF(J9="","",WORKDAY(J9+4,1)) -> 46321 | L9: 46321 | O9: Relancé
A10: 9 | B10: CCI | C10: CCI Paris Île-de-France (Val-d'Oise) | D10: Île-de-France | E10: creation95@cci-paris-idf.fr | F10: Tiers (valparisis.fr) | G10: Check-list + simulateurs | H10: Un outil gratuit pour vos porteurs de projet (facture électronique 2027) | I10: Envoyé | J10: 46318 | K10: =IF(J10="","",WORKDAY(J10+4,1)) -> 46323 | O10: Relance prévue le 28/10/2026
A11: 10 | B11: CCI | C11: CCI Bretagne | D11: Bretagne | E11: ccir@bretagne.cci.fr | F11: Officiel ancien (douane.gouv.fr), à vérifier | G11: Check-list + simulateurs | H11: Un outil gratuit pour vos porteurs de projet (facture électronique 2027) | I11: Relancé | J11: 46314 | K11: =IF(J11="","",WORKDAY(J11+4,1)) -> 46321 | L11: 46321 | O11: Relancé
A12: 11 | B12: CCI | C12: CCI Hauts-de-France | D12: Hauts-de-France | E12: ccideregion@hautsdefrance.cci.fr | F12: Tiers (document CCI repris) | G12: Check-list + simulateurs | H12: Un outil gratuit pour vos porteurs de projet (facture électronique 2027) | I12: Adresse invalide | J12: 46318 | K12: =IF(J12="","",WORKDAY(J12+4,1)) -> 46323 | O12: 23/10 : rebond, message bloqué par le serveur de CCI Hauts-de-France. Pas de relance.
A13: 12 | B13: CCI | C13: CCI Ouest Normandie | D13: Normandie | E13: cci@normandie.cci.fr | F13: Tiers (annuaire-administration.com) | G13: Check-list + simulateurs | H13: Un outil gratuit pour vos porteurs de projet (facture électronique 2027) | I13: Adresse invalide | J13: 46318 | K13: =IF(J13="","",WORKDAY(J13+4,1)) -> 46323 | O13: 23/10 : rebond, message bloqué par le serveur de CCI Ouest Normandie. Pas de relance.
A14: 13 | B14: CCI | C14: CCI Portes de Normandie | D14: Normandie | E14: info-eure@normandie.cci.fr | F14: Tiers (annuaire-administration.com) | G14: Check-list + simulateurs | H14: Un outil gratuit pour vos porteurs de projet (facture électronique 2027) | I14: Envoyé | J14: 46318 | K14: =IF(J14="","",WORKDAY(J14+4,1)) -> 46323 | O14: Relance prévue le 28/10/2026
A15: 14 | B15: CCI | C15: CCI Nouvelle-Aquitaine | D15: Nouvelle-Aquitaine | E15: contact@nouvelle-aquitaine.cci.fr | F15: Tiers (annuaire-administration.com) | G15: Check-list + simulateurs | H15: Un outil gratuit pour vos porteurs de projet (facture électronique 2027) | I15: Envoyé | J15: 46318 | K15: =IF(J15="","",WORKDAY(J15+4,1)) -> 46323 | O15: Relance prévue le 28/10/2026
A16: 15 | B16: CCI | C16: CCI Nantes St-Nazaire (création-reprise) | D16: Pays de la Loire | E16: conseil-creation-reprise@44.cci.fr | F16: Tiers, source non relevée : à vérifier | G16: Check-list + simulateurs | H16: Un outil gratuit pour vos porteurs de projet (facture électronique 2027) | I16: Envoyé | J16: 46318 | K16: =IF(J16="","",WORKDAY(J16+4,1)) -> 46323 | O16: Relance prévue le 28/10/2026
A17: 16 | B17: CMA | C17: CMA Val-d'Oise | D17: Île-de-France | E17: eco@cma95.fr | F17: Tiers (valparisis.fr) | G17: Check-list artisans | H17: Facture électronique 2027 : une check-list gratuite pour les artisans | I17: Adresse invalide | J17: 46318 | K17: =IF(J17="","",WORKDAY(J17+4,1)) -> 46323 | O17: 23/10 : rebond, message bloqué par le serveur de CMA Val-d'Oise. Pas de relance.
A18: 17 | B18: CMA | C18: CMA Auvergne-Rhône-Alpes | D18: Auvergne-Rhône-Alpes | E18: contact@crma-auvergnerhonealpes.fr | F18: Tiers, 2018 : peut être obsolète | G18: Check-list artisans | H18: Facture électronique 2027 : une check-list gratuite pour les artisans | I18: Envoyé | J18: 46318 | K18: =IF(J18="","",WORKDAY(J18+4,1)) -> 46323 | O18: 23/10 : réponse automatique, l'adresse n'est plus suivie : contacter la CMA départementale. Relance prévue le 28/10/2026.
A19: 18 | B19: CMA | C19: CMA Côte-d'Or | D19: Bourgogne-Franche-Comté | E19: accueil-s21@artisanat-bfc.fr | F19: Tiers (annuaire-administration.com) | G19: Check-list artisans | H19: Facture électronique 2027 : une check-list gratuite pour les artisans | I19: Envoyé | J19: 46318 | K19: =IF(J19="","",WORKDAY(J19+4,1)) -> 46323 | O19: Relance prévue le 28/10/2026
A20: 19 | B20: CMA | C20: CMA Morbihan | D20: Bretagne | E20: accueil@cma-morbihan.fr | F20: Tiers (annuaire-administration.com) | G20: Check-list artisans | H20: Facture électronique 2027 : une check-list gratuite pour les artisans | I20: Envoyé | J20: 46318 | K20: =IF(J20="","",WORKDAY(J20+4,1)) -> 46323 | O20: Relance prévue le 28/10/2026
A21: 20 | B21: CMA | C21: CMA Loiret | D21: Centre-Val de Loire | E21: contact@cma45.fr | F21: Tiers (annuaire-administration.com) | G21: Check-list artisans | H21: Facture électronique 2027 : une check-list gratuite pour les artisans | I21: Brouillon prêt | K21: =IF(J21="","",WORKDAY(J21+4,1)) | O21: Envoi conseillé : jour 6
A22: 21 | B22: CMA | C22: CMA Alsace | D22: Grand Est | E22: cma@cm-alsace.fr | F22: Tiers (strasbourg-europe.eu) | G22: Check-list artisans | H22: Facture électronique 2027 : une check-list gratuite pour les artisans | I22: Brouillon prêt | K22: =IF(J22="","",WORKDAY(J22+4,1)) | O22: Envoi conseillé : jour 6
A23: 22 | B23: CMA | C23: CMA Hauts-de-France | D23: Hauts-de-France | E23: contact@cma-hautsdefrance.fr | F23: Tiers (annuaire-administration.com) | G23: Check-list artisans | H23: Facture électronique 2027 : une check-list gratuite pour les artisans | I23: Brouillon prêt | K23: =IF(J23="","",WORKDAY(J23+4,1)) | O23: Envoi conseillé : jour 6
A24: 23 | B24: CMA | C24: CMA Charente | D24: Nouvelle-Aquitaine | E24: 16-eco@cma-nouvelleaquitaine.fr | F24: Tiers (document de commune) | G24: Check-list artisans | H24: Facture électronique 2027 : une check-list gratuite pour les artisans | I24: Brouillon prêt | K24: =IF(J24="","",WORKDAY(J24+4,1)) | O24: Envoi conseillé : jour 6
A25: 24 | B25: CMA | C25: CMA Vienne | D25: Nouvelle-Aquitaine | E25: 86-cma-info@cma-nouvelleaquitaine.fr | F25: Tiers (lavienne86.fr) | G25: Check-list artisans | H25: Facture électronique 2027 : une check-list gratuite pour les artisans | I25: Brouillon prêt | K25: =IF(J25="","",WORKDAY(J25+4,1)) | O25: Envoi conseillé : jour 6
A26: 25 | B26: CMA | C26: CMA Loire-Atlantique | D26: Pays de la Loire | E26: entreprises44@cma-paysdelaloire.fr | F26: Officiel, à revérifier | G26: Check-list artisans | H26: Facture électronique 2027 : une check-list gratuite pour les artisans | I26: Relancé | J26: 46314 | K26: =IF(J26="","",WORKDAY(J26+4,1)) -> 46321 | L26: 46321 | O26: Relancé
A27: 26 | B27: CMA | C27: CMA Alpes-Maritimes | D27: PACA | E27: contact06@cmar-paca.fr | F27: Tiers (annuaire-administration.com) | G27: Check-list artisans | H27: Facture électronique 2027 : une check-list gratuite pour les artisans | I27: Brouillon prêt | K27: =IF(J27="","",WORKDAY(J27+4,1)) | O27: Envoi conseillé : jour 6
A28: 27 | B28: Réseau | C28: BGE Réseau (national) | D28: National | E28: accueil@bge.asso.fr | F28: Officiel (bge.asso.fr, 2024) | G28: Simulateurs + check-list | H28: Des outils gratuits pour les entrepreneurs que vous accompagnez | I28: Adresse invalide | J28: 46314 | K28: =IF(J28="","",WORKDAY(J28+4,1)) -> 46321 | O28: Réponse auto 19/10 : boîte plus relevée. Pas de relance. Viser les BGE régionales.
A29: 28 | B29: CCI | C29: CCI Réunion (conseil entreprise) | D29: La Réunion | E29: conseilentreprise@reunion.cci.fr | F29: Officiel (page d’environ 5 ans) | G29: Check-list + simulateurs | H29: Un outil gratuit pour vos porteurs de projet (facture électronique 2027) | I29: Relancé | J29: 46314 | K29: =IF(J29="","",WORKDAY(J29+4,1)) -> 46321 | L29: 46321 | O29: Relancé
A30: 29 | B30: CCI | C30: CCI Loiret | D30: Centre-Val de Loire | E30: entreprendre@loiret.cci.fr | F30: Officiel (centre.cci.fr) | G30: Check-list + simulateurs | H30: Un outil gratuit pour vos porteurs de projet (facture électronique 2027) | I30: Relancé | J30: 46314 | K30: =IF(J30="","",WORKDAY(J30+4,1)) -> 46321 | L30: 46321 | O30: Relancé
A31: 30 | B31: CCI | C31: CCI Cher, Espace Entreprendre | D31: Centre-Val de Loire | E31: espace-entreprendre@cher.cci.fr | F31: Officiel (centre.cci.fr) | G31: Check-list + simulateurs | H31: Un outil gratuit pour vos porteurs de projet (facture électronique 2027) | I31: Relancé | J31: 46314 | K31: =IF(J31="","",WORKDAY(J31+4,1)) -> 46321 | L31: 46321 | O31: Relancé
A32: 31 | B32: CCI | C32: CCI Indre | D32: Centre-Val de Loire | E32: entreprendre@indre.cci.fr | F32: Officiel (centre.cci.fr) | G32: Check-list + simulateurs | H32: Un outil gratuit pour vos porteurs de projet (facture électronique 2027) | I32: Relancé | J32: 46315 | K32: =IF(J32="","",WORKDAY(J32+4,1)) -> 46321 | L32: 46321 | O32: Relancé
A33: 32 | B33: CCI | C33: CCI Loir-et-Cher | D33: Centre-Val de Loire | E33: entreprendre@41.cci.fr | F33: Officiel (centre.cci.fr) | G33: Check-list + simulateurs | H33: Un outil gratuit pour vos porteurs de projet (facture électronique 2027) | I33: Relancé | J33: 46315 | K33: =IF(J33="","",WORKDAY(J33+4,1)) -> 46321 | L33: 46321 | O33: Relancé
A34: 33 | B34: CCI | C34: CCI Vendée, Espace Création | D34: Pays de la Loire | E34: espace.creation@vendee.cci.fr | F34: Officiel (paysdelaloire.cci.fr) | G34: Check-list + simulateurs | H34: Un outil gratuit pour vos porteurs de projet (facture électronique 2027) | I34: Relancé | J34: 46315 | K34: =IF(J34="","",WORKDAY(J34+4,1)) -> 46321 | L34: 46321 | O34: Relancé
A35: 34 | B35: CCI | C35: CCI Tarn | D35: Occitanie | E35: monprojetaveclacci@tarn.cci.fr | F35: Officiel (tarn.cci.fr) | G35: Check-list + simulateurs | H35: Un outil gratuit pour vos porteurs de projet (facture électronique 2027) | I35: Relancé | J35: 46315 | K35: =IF(J35="","",WORKDAY(J35+4,1)) -> 46321 | L35: 46321 | O35: Relancé
A36: 35 | B36: CCI | C36: CCI Alpes-de-Haute-Provence | D36: PACA | E36: creation@digne.cci.fr | F36: Officiel (digne.cci.fr) | G36: Check-list + simulateurs | H36: Un outil gratuit pour vos porteurs de projet (facture électronique 2027) | I36: Relancé | J36: 46315 | K36: =IF(J36="","",WORKDAY(J36+4,1)) -> 46321 | L36: 46321 | O36: Relancé
A37: 36 | B37: CCI | C37: CCI Métropole de Bourgogne, Espace Entreprendre | D37: Bourgogne-Franche-Comté | E37: espace.entreprendre@mdb.cci.fr | F37: Officiel (metropoledebourgogne.cci.fr) | G37: Check-list + simulateurs | H37: Un outil gratuit pour vos porteurs de projet (facture électronique 2027) | I37: Relancé | J37: 46315 | K37: =IF(J37="","",WORKDAY(J37+4,1)) -> 46321 | L37: 46321 | O37: Relancé
A38: 37 | B38: CCI | C38: CCI Lyon Métropole | D38: Auvergne-Rhône-Alpes | E38: infos@lyon-metropole.cci.fr | F38: Officiel (contact général) | G38: Check-list + simulateurs | H38: Un outil gratuit pour vos porteurs de projet (facture électronique 2027) | I38: Relancé | J38: 46315 | K38: =IF(J38="","",WORKDAY(J38+4,1)) -> 46321 | L38: 46321 | O38: Relancé
A39: 38 | B39: CCI | C39: CCI PACA | D39: PACA | E39: information@paca.cci.fr | F39: Officiel (contact général) | G39: Check-list + simulateurs | H39: Un outil gratuit pour vos porteurs de projet (facture électronique 2027) | I39: Relancé | J39: 46315 | K39: =IF(J39="","",WORKDAY(J39+4,1)) -> 46321 | L39: 46321 | O39: Relancé
A40: 39 | B40: CMA | C40: CMA Pyrénées-Orientales | D40: Occitanie | E40: contact@cma66.fr | F40: Officiel (annuaire service-public.gouv.fr) | G40: Check-list artisans | H40: Facture électronique 2027 : une check-list gratuite pour les artisans | I40: Relancé | J40: 46315 | K40: =IF(J40="","",WORKDAY(J40+4,1)) -> 46321 | L40: 46321 | O40: Relancé
A41: 40 | B41: CMA | C41: CMA Val-de-Marne | D41: Île-de-France | E41: contact@cma94.com | F41: Tiers (annuaire-administration.com) | G41: Check-list artisans | H41: Facture électronique 2027 : une check-list gratuite pour les artisans | I41: Brouillon prêt | K41: =IF(J41="","",WORKDAY(J41+4,1)) | O41: Envoi conseillé : jour 6
A42: 41 | B42: CMA | C42: CMA Île-de-France, Paris | D42: Île-de-France | E42: contact@cma-paris.fr | F42: Officiel (cma-idf.fr) | G42: Check-list artisans | H42: Facture électronique 2027 : une check-list gratuite pour les artisans | I42: Refus | J42: 46315 | K42: =IF(J42="","",WORKDAY(J42+4,1)) -> 46321 | M42: Oui | O42: 20/10 : réponse STOP de contact.75@cma-idf.fr. Plus aucun mail.
A43: 42 | B43: CMA | C43: CMA Rhône | D43: Auvergne-Rhône-Alpes | E43: contact@cma-auvergnerhonealpes.fr | F43: Officiel (annuaire service-public.gouv.fr) | G43: Check-list artisans | H43: Facture électronique 2027 : une check-list gratuite pour les artisans | I43: Relancé | J43: 46315 | K43: =IF(J43="","",WORKDAY(J43+4,1)) -> 46321 | L43: 46321 | O43: Relancé
A44: 43 | B44: CMA | C44: CMA Grand Est (Metz) | D44: Grand Est | E44: contact@cma-grand-est.com | F44: Officiel (cma-alsace-moselle-grandest.fr) | G44: Check-list artisans | H44: Facture électronique 2027 : une check-list gratuite pour les artisans | I44: Adresse invalide | J44: 46315 | K44: =IF(J44="","",WORKDAY(J44+4,1)) -> 46321 | O44: 20/10 : rebond, domaine cma-grand-est.com introuvable. Pas de relance.
A45: 44 | B45: CMA | C45: CMA Bouches-du-Rhône | D45: PACA | E45: contact13@cmar-paca.fr | F45: Officiel (annuaire service-public.gouv.fr) | G45: Check-list artisans | H45: Facture électronique 2027 : une check-list gratuite pour les artisans | I45: Relancé | J45: 46315 | K45: =IF(J45="","",WORKDAY(J45+4,1)) -> 46321 | L45: 46321 | O45: Relancé
A46: 45 | B46: CMA | C46: CMA Sarthe | D46: Pays de la Loire | E46: contact72@cma-paysdelaloire.fr | F46: Officiel (annuaire service-public.gouv.fr) | G46: Check-list artisans | H46: Facture électronique 2027 : une check-list gratuite pour les artisans | I46: Envoyé | J46: 46317 | K46: =IF(J46="","",WORKDAY(J46+4,1)) -> 46322 | O46: Relance prévue le 27/10/2026
A47: 46 | B47: CMA | C47: CMA Hérault | D47: Occitanie | E47: cma34@cma-herault.fr | F47: Officiel (annuaire service-public.gouv.fr) | G47: Check-list artisans | H47: Facture électronique 2027 : une check-list gratuite pour les artisans | I47: Relancé | J47: 46316 | K47: =IF(J47="","",WORKDAY(J47+4,1)) -> 46321 | L47: 46321 | O47: Relancé
A48: 47 | B48: CMA | C48: CMA Gironde | D48: Nouvelle-Aquitaine | E48: bonjour@cma-nouvelle-aquitaine.fr | F48: Officiel, mais domaine différent de cma-nouvelleaquitaine.fr : à surveiller | G48: Check-list artisans | H48: Facture électronique 2027 : une check-list gratuite pour les artisans | I48: Relancé | J48: 46316 | K48: =IF(J48="","",WORKDAY(J48+4,1)) -> 46321 | L48: 46321 | O48: Relancé
A49: 48 | B49: Initiative | C49: Initiative Sarthe | D49: Pays de la Loire | E49: contact@initiative-sarthe.fr | F49: Tiers (les-aides.fr) | G49: Simulateurs + check-list | H49: Des outils gratuits pour les créateurs que vous accompagnez | I49: Brouillon prêt | K49: =IF(J49="","",WORKDAY(J49+4,1)) | O49: Envoi conseillé : jour 6
A50: 49 | B50: Initiative | C50: Initiative Orne | D50: Normandie | E50: contact@initiative-orne.com | F50: Officiel (plaquette) | G50: Simulateurs + check-list | H50: Des outils gratuits pour les créateurs que vous accompagnez | I50: Adresse invalide | J50: 46316 | K50: =IF(J50="","",WORKDAY(J50+4,1)) -> 46321 | O50: 21/10 : rebond, domaine initiative-orne.com introuvable. Pas de relance.
A51: 50 | B51: Initiative | C51: Initiative Genevois | D51: Auvergne-Rhône-Alpes | E51: contact@initiative-genevois.fr | F51: Tiers (les-aides.fr) | G51: Simulateurs + check-list | H51: Des outils gratuits pour les créateurs que vous accompagnez | I51: Brouillon prêt | K51: =IF(J51="","",WORKDAY(J51+4,1)) | O51: Envoi conseillé : jour 6
A52: 51 | B52: Initiative | C52: Initiative Rouen | D52: Normandie | E52: rouen-initiative@rouen.cci.fr | F52: Tiers (les-aides.fr) | G52: Simulateurs + check-list | H52: Des outils gratuits pour les créateurs que vous accompagnez | I52: Brouillon prêt | K52: =IF(J52="","",WORKDAY(J52+4,1)) | O52: Envoi conseillé : jour 6
A53: 52 | B53: Initiative | C53: Initiative Sud Grésivaudan Royans Vercors | D53: Auvergne-Rhône-Alpes | E53: contact@initiative-sgrv.fr | F53: Tiers (les-aides.fr) | G53: Simulateurs + check-list | H53: Des outils gratuits pour les créateurs que vous accompagnez | I53: Brouillon prêt | K53: =IF(J53="","",WORKDAY(J53+4,1)) | O53: Envoi conseillé : jour 6
A54: 53 | B54: Initiative | C54: Initiative Alpes-de-Haute-Provence | D54: PACA | E54: contact@initiative-alpesdehauteprovence.com | F54: Tiers (les-aides.fr) | G54: Simulateurs + check-list | H54: Des outils gratuits pour les créateurs que vous accompagnez | I54: Brouillon prêt | K54: =IF(J54="","",WORKDAY(J54+4,1)) | O54: Envoi conseillé : jour 6
A55: 54 | B55: Initiative | C55: Initiative Calvados | D55: Normandie | E55: contact@initiative-calvados.fr | F55: Tiers (le site n’affiche qu’un formulaire) | G55: Simulateurs + check-list | H55: Des outils gratuits pour les créateurs que vous accompagnez | I55: Brouillon prêt | K55: =IF(J55="","",WORKDAY(J55+4,1)) | O55: Envoi conseillé : jour 6
A56: 55 | B56: Initiative | C56: Initiative Var | D56: PACA | E56: info@initiative-var.fr | F56: Officiel (initiative-var.fr) | G56: Simulateurs + check-list | H56: Des outils gratuits pour les créateurs que vous accompagnez | I56: Relancé | J56: 46316 | K56: =IF(J56="","",WORKDAY(J56+4,1)) -> 46321 | L56: 46321 | O56: Relancé
A57: 56 | B57: Initiative | C57: Initiative Terres de Vaucluse | D57: PACA | E57: contact@initiativeterresdevaucluse.fr | F57: Officiel (site de la plateforme) | G57: Simulateurs + check-list | H57: Des outils gratuits pour les créateurs que vous accompagnez | I57: Relancé | J57: 46316 | K57: =IF(J57="","",WORKDAY(J57+4,1)) -> 46321 | L57: 46321 | O57: Relancé
A58: 57 | B58: Initiative | C58: Initiative Vallée de la Drôme Diois | D58: Auvergne-Rhône-Alpes | E58: contact@initiative-valleedeladromediois.fr | F58: Tiers (liste ancienne) | G58: Simulateurs + check-list | H58: Des outils gratuits pour les créateurs que vous accompagnez | I58: Brouillon prêt | K58: =IF(J58="","",WORKDAY(J58+4,1)) | O58: Envoi conseillé : jour 7
A59: 58 | B59: Réseau Entreprendre | C59: Réseau Entreprendre (fédération) | D59: National | E59: reseau@reseau-entreprendre.org | F59: Officiel (rapport financier 2024) | G59: Simulateurs + check-list | H59: Des ressources gratuites pour les dirigeants que vous accompagnez | I59: Adresse invalide | J59: 46316 | K59: =IF(J59="","",WORKDAY(J59+4,1)) -> 46321 | O59: 21/10 : rebond, message bloqué par le serveur de Réseau Entreprendre. Pas de relance.
A60: 59 | B60: Réseau Entreprendre | C60: Réseau Entreprendre Lorraine | D60: Grand Est | E60: lorraine@reseau-entreprendre.org | F60: Officiel (page contact) | G60: Simulateurs + check-list | H60: Des ressources gratuites pour les dirigeants que vous accompagnez | I60: Relancé | J60: 46316 | K60: =IF(J60="","",WORKDAY(J60+4,1)) -> 46321 | L60: 46321 | O60: Relancé
A61: 60 | B61: Réseau Entreprendre | C61: Réseau Entreprendre Val-de-Marne | D61: Île-de-France | E61: valdemarne@reseau-entreprendre.org | F61: Officiel (page contact) | G61: Simulateurs + check-list | H61: Des ressources gratuites pour les dirigeants que vous accompagnez | I61: Relancé | J61: 46316 | K61: =IF(J61="","",WORKDAY(J61+4,1)) -> 46321 | L61: 46321 | O61: Relancé
A62: 61 | B62: Réseau Entreprendre | C62: Réseau Entreprendre Aquitaine | D62: Nouvelle-Aquitaine | E62: aquitaine@reseau-entreprendre.org | F62: Officiel (page contact) | G62: Simulateurs + check-list | H62: Des ressources gratuites pour les dirigeants que vous accompagnez | I62: Relancé | J62: 46316 | K62: =IF(J62="","",WORKDAY(J62+4,1)) -> 46321 | L62: 46321 | O62: Relancé
A63: 62 | B63: Réseau Entreprendre | C63: Réseau Entreprendre Yvelines | D63: Île-de-France | E63: yvelines@reseau-entreprendre.org | F63: Officiel (page contact) | G63: Simulateurs + check-list | H63: Des ressources gratuites pour les dirigeants que vous accompagnez | I63: Relancé | J63: 46316 | K63: =IF(J63="","",WORKDAY(J63+4,1)) -> 46321 | L63: 46321 | O63: Relancé
A64: 63 | B64: Réseau Entreprendre | C64: Réseau Entreprendre Rhône-Durance | D64: PACA | E64: rhone-durance@reseau-entreprendre.org | F64: Officiel (page contact) | G64: Simulateurs + check-list | H64: Des ressources gratuites pour les dirigeants que vous accompagnez | I64: Relancé | J64: 46316 | K64: =IF(J64="","",WORKDAY(J64+4,1)) -> 46321 | L64: 46321 | O64: Relancé
A65: 64 | B65: Réseau Entreprendre | C65: Réseau Entreprendre Loire | D65: Auvergne-Rhône-Alpes | E65: loire@reseau-entreprendre.org | F65: Officiel (page contact) | G65: Simulateurs + check-list | H65: Des ressources gratuites pour les dirigeants que vous accompagnez | I65: Relancé | J65: 46316 | K65: =IF(J65="","",WORKDAY(J65+4,1)) -> 46321 | L65: 46321 | O65: Relancé
A66: 65 | B66: Réseau Entreprendre | C66: Réseau Entreprendre Atlantique | D66: Pays de la Loire | E66: atlantique@reseau-entreprendre.org | F66: Tiers (document de 2019) | G66: Simulateurs + check-list | H66: Des ressources gratuites pour les dirigeants que vous accompagnez | I66: Brouillon prêt | K66: =IF(J66="","",WORKDAY(J66+4,1)) | O66: Envoi conseillé : jour 7
A67: 66 | B67: Couveuse / CAE | C67: Union des couveuses d’entreprises | D67: National | E67: contact@uniondescouveuses.com | F67: Officiel (jetestemonentreprise.com) | G67: Calculateur TJM + check-list | H67: Un calculateur de TJM gratuit pour les entrepreneurs à l’essai | I67: Envoyé | J67: 46317 | K67: =IF(J67="","",WORKDAY(J67+4,1)) -> 46322 | O67: 22/10 : filtre anti-spam Mailinblack, expéditeur validé le 23/10, message délivré. Relance prévue le 27/10/2026.
A68: 67 | B68: Couveuse / CAE | C68: Coopérer pour entreprendre | D68: National | E68: info@cooperer.coop | F68: Tiers (annuaire Avise) | G68: Calculateur TJM + check-list | H68: Un calculateur de TJM gratuit pour les entrepreneurs-salariés | I68: Brouillon prêt | K68: =IF(J68="","",WORKDAY(J68+4,1)) | O68: Envoi conseillé : jour 7
A69: 68 | B69: Couveuse / CAE | C69: Coopérer pour entreprendre Bretagne | D69: Bretagne | E69: bretagne@cooperer.coop | F69: Tiers (ess-bretagne.org) | G69: Calculateur TJM + check-list | H69: Un calculateur de TJM gratuit pour les entrepreneurs-salariés | I69: Brouillon prêt | K69: =IF(J69="","",WORKDAY(J69+4,1)) | O69: Envoi conseillé : jour 7
A70: 69 | B70: Couveuse / CAE | C70: Fédération des CAE | D70: National | E70: les-cae@scop.coop | F70: Tiers (ambition-ess.org) | G70: Calculateur TJM + check-list | H70: Un calculateur de TJM gratuit pour les entrepreneurs-salariés | I70: Brouillon prêt | K70: =IF(J70="","",WORKDAY(J70+4,1)) | O70: Envoi conseillé : jour 7
A71: 70 | B71: Couveuse / CAE | C71: URSCOP Nouvelle-Aquitaine | D71: Nouvelle-Aquitaine | E71: urnouvelleaquitaine@scop.coop | F71: Officiel (les-scop-nouvelle-aquitaine.coop) | G71: Check-list + TJM | H71: Facture électronique 2027 : une check-list gratuite pour les CAE | I71: Envoyé | J71: 46317 | K71: =IF(J71="","",WORKDAY(J71+4,1)) -> 46322 | O71: Relance prévue le 27/10/2026
A72: 71 | B72: Couveuse / CAE | C72: Cabestan (CAE) | D72: Auvergne-Rhône-Alpes | E72: contact@cabestan.fr | F72: Tiers (plaquette) | G72: Calculateur TJM + check-list | H72: Un calculateur de TJM gratuit pour les entrepreneurs-salariés | I72: Brouillon prêt | K72: =IF(J72="","",WORKDAY(J72+4,1)) | O72: Envoi conseillé : jour 7
A73: 72 | B73: Couveuse / CAE | C73: CoopConnexion (CAE) | D73: Hauts-de-France | E73: contact@coopconnexion.fr | F73: Officiel (coopconnexion.fr) | G73: Calculateur TJM + check-list | H73: Un calculateur de TJM gratuit pour les entrepreneurs-salariés | I73: Envoyé | J73: 46317 | K73: =IF(J73="","",WORKDAY(J73+4,1)) -> 46322 | O73: Relance prévue le 27/10/2026
A74: 73 | B74: Couveuse / CAE | C74: Coopetic (CAE) | D74: Île-de-France | E74: contact@coopetic.coop | F74: Officiel (coopetic.coop) | G74: Calculateur TJM + check-list | H74: Un calculateur de TJM gratuit pour les entrepreneurs-salariés | I74: Envoyé | J74: 46317 | K74: =IF(J74="","",WORKDAY(J74+4,1)) -> 46322 | O74: Relance prévue le 27/10/2026
A75: 74 | B75: Couveuse / CAE | C75: Coopilote (CAE) | D75: Bourgogne-Franche-Comté | E75: administratif@coopilote.com | F75: Officiel (coopilote.com), adresse administrative | G75: Check-list + TJM | H75: Facture électronique 2027 : une check-list gratuite pour vos entrepreneurs | I75: Envoyé | J75: 46317 | K75: =IF(J75="","",WORKDAY(J75+4,1)) -> 46322 | O75: Relance prévue le 27/10/2026
A76: 75 | B76: Couveuse / CAE | C76: Le Comptoir des Entrepreneurs (CAE) | D76: Occitanie | E76: contact@lecomptoirdesentrepreneurs.fr | F76: Tiers (fiche les-scop.coop) | G76: Calculateur TJM + check-list | H76: Un calculateur de TJM gratuit pour les entrepreneurs-salariés | I76: Brouillon prêt | K76: =IF(J76="","",WORKDAY(J76+4,1)) | O76: Envoi conseillé : jour 7
A77: 76 | B77: Couveuse / CAE | C77: Coopenates (CAE) | D77: Grand Est | E77: contact@coopenates.com | F77: Tiers (fiche les-cae.coop) | G77: Calculateur TJM + check-list | H77: Un calculateur de TJM gratuit pour les entrepreneurs-salariés | I77: Brouillon prêt | K77: =IF(J77="","",WORKDAY(J77+4,1)) | O77: Envoi conseillé : jour 7
A78: 77 | B78: Média | C78: Widoobiz | D78: National | E78: redaction@widoobiz.com | F78: Officiel (page d’environ 6 ans) | G78: Baromètre des prix + TJM | H78: 83 % des logiciels de caisse cachent leurs prix (étude TPE 2027) | I78: Adresse invalide | J78: 46317 | K78: =IF(J78="","",WORKDAY(J78+4,1)) -> 46322 | O78: 22/10 : rebond, message bloqué par le serveur de Widoobiz. Pas de relance.
A79: 78 | B79: Média | C79: Le Journal des Entreprises | D79: National | E79: redacweb@lejournaldesentreprises.com | F79: Tiers (leadiq.com), non confirmée | G79: Check-list + baromètre | H79: Facture électronique 2027 : une check-list gratuite pour les TPE | I79: Brouillon prêt | K79: =IF(J79="","",WORKDAY(J79+4,1)) | O79: Envoi conseillé : jour 7
A80: 79 | B80: Média | C80: Espace Auto-Entrepreneur | D80: National | E80: contact@espace-autoentrepreneur.com | F80: Officiel (page presse) | G80: Simulateurs charges + TVA | H80: Des simulateurs gratuits pour vos lecteurs auto-entrepreneurs | I80: Envoyé | J80: 46317 | K80: =IF(J80="","",WORKDAY(J80+4,1)) -> 46322 | O80: 22/10 : accusé de réception automatique (demande 487253). Relance prévue le 27/10/2026.
A81: 80 | B81: Média | C81: Le Courrier des Entreprises | D81: Auvergne-Rhône-Alpes | E81: contact@lecourrierdesentreprises.fr | F81: Officiel (site) | G81: Check-list + baromètre | H81: Facture électronique 2027 : une check-list gratuite pour les TPE | I81: Envoyé | J81: 46317 | K81: =IF(J81="","",WORKDAY(J81+4,1)) -> 46322 | O81: Relance prévue le 27/10/2026
A82: 81 | B82: Fédération | C82: SDI (Syndicat des indépendants et TPE) | D82: National | E82: contact@sdi-pme.fr | F82: Officiel (page contact) | G82: Check-list + simulateurs | H82: Facture électronique 2027 : une check-list gratuite pour vos adhérents | I82: Envoyé | J82: 46317 | K82: =IF(J82="","",WORKDAY(J82+4,1)) -> 46322 | O82: Relance prévue le 27/10/2026
A83: 82 | B83: Fédération | C83: UNION-Indépendants | D83: National | E83: contact@union-independants.fr | F83: Officiel (arpe.gouv.fr) | G83: Calculateur TJM + check-list | H83: Un calculateur de TJM gratuit pour les indépendants | I83: Envoyé | J83: 46317 | K83: =IF(J83="","",WORKDAY(J83+4,1)) -> 46322 | O83: Relance prévue le 27/10/2026
A84: 83 | B84: Fédération | C84: PEPS (portage salarial) | D84: National | E84: presse@peps-syndicat.fr | F84: Officiel (peps-syndicat.fr) | G84: Calculateur TJM + baromètre | H84: Un calculateur de TJM gratuit pour les consultants indépendants | I84: Envoyé | J84: 46317 | K84: =IF(J84="","",WORKDAY(J84+4,1)) -> 46322 | O84: Relance prévue le 27/10/2026
A85: 84 | B85: Association | C85: 60 000 rebonds | D85: National | E85: contact@60000rebonds.com | F85: Officiel (variante en .fr ailleurs) | G85: Simulateurs + check-list | H85: Des simulateurs gratuits pour les entrepreneurs qui rebondissent | I85: Envoyé | J85: 46317 | K85: =IF(J85="","",WORKDAY(J85+4,1)) -> 46322 | O85: Relance prévue le 27/10/2026
A86: 85 | B86: Association | C86: 60 000 rebonds Bourgogne-Franche-Comté | D86: Bourgogne-Franche-Comté | E86: bfc@60000rebonds.com | F86: Officiel (page régionale) | G86: Simulateurs + check-list | H86: Des simulateurs gratuits pour les entrepreneurs qui rebondissent | I86: Envoyé | J86: 46318 | K86: =IF(J86="","",WORKDAY(J86+4,1)) -> 46323 | O86: Relance prévue le 28/10/2026
A87: 86 | B87: Association | C87: Moovjee (mentorat) | D87: National | E87: moovjee@twoo-mentorat.fr | F87: Officiel (moovjee.fr) | G87: Simulateurs + TJM | H87: Des outils gratuits pour les jeunes entrepreneurs que vous accompagnez | I87: Envoyé | J87: 46318 | K87: =IF(J87="","",WORKDAY(J87+4,1)) -> 46323 | O87: Relance prévue le 28/10/2026
A88: 87 | B88: Expert-comptable | C88: Ordre des experts-comptables Paris IDF | D88: Île-de-France | E88: contact@oec-paris.fr | F88: Officiel (annuaire service-public.gouv.fr) | G88: Check-list facture électronique | H88: Facture électronique 2027 : une check-list gratuite pour les clients TPE des cabinets | I88: Envoyé | J88: 46318 | K88: =IF(J88="","",WORKDAY(J88+4,1)) -> 46323 | O88: 23/10 : réponse automatique de l'Ordre (attestations, espace pro). Relance prévue le 28/10/2026.
A89: 88 | B89: Expert-comptable | C89: ECF (syndicat des experts-comptables) | D89: National | E89: contact@e-c-f.fr | F89: Officiel (page Facebook) | G89: Check-list facture électronique | H89: Facture électronique 2027 : une check-list gratuite pour les clients TPE des cabinets | I89: Brouillon prêt | K89: =IF(J89="","",WORKDAY(J89+4,1)) | O89: Envoi conseillé : jour 5
A90: 89 | B90: Réseau | C90: BGE Hauts-de-France | D90: Hauts-de-France | E90: contact@bge-hautsdefrance.fr | F90: Officiel (site BGE, extrait de recherche), doc 2019 | G90: Simulateurs + check-list | H90: Des outils gratuits pour les créateurs que vous accompagnez | I90: Brouillon prêt | K90: =IF(J90="","",WORKDAY(J90+4,1)) | O90: Envoi conseillé : jour 7
A91: 90 | B91: Réseau | C91: BGE Picardie | D91: Hauts-de-France | E91: contact@bge-picardie.org | F91: Officiel (site BGE, extrait de recherche) | G91: Simulateurs + check-list | H91: Des outils gratuits pour les créateurs que vous accompagnez | I91: Brouillon prêt | K91: =IF(J91="","",WORKDAY(J91+4,1)) | O91: Envoi conseillé : jour 7
A92: 91 | B92: Réseau | C92: BGE PaRIF | D92: Île-de-France | E92: contact@bge-parif.com | F92: Tiers (flyer Versailles Grand Parc, 2021) | G92: Simulateurs + check-list | H92: Des outils gratuits pour les créateurs que vous accompagnez | I92: Brouillon prêt | K92: =IF(J92="","",WORKDAY(J92+4,1)) | O92: Envoi conseillé : jour 7
A93: 92 | B93: Réseau | C93: BGE Flandre Création | D93: Hauts-de-France | E93: contact@bge-flandrecreation.fr | F93: Tiers (dossier Agefice, 2019) | G93: Simulateurs + check-list | H93: Des outils gratuits pour les créateurs que vous accompagnez | I93: Brouillon prêt | K93: =IF(J93="","",WORKDAY(J93+4,1)) | O93: Envoi conseillé : jour 7
A94: 93 | B94: Réseau | C94: BGE Auvergne | D94: Auvergne-Rhône-Alpes | E94: contact@bgeauvergne.fr | F94: Tiers (proposition Agefice, 2019) | G94: Simulateurs + check-list | H94: Des outils gratuits pour les créateurs que vous accompagnez | I94: Brouillon prêt | K94: =IF(J94="","",WORKDAY(J94+4,1)) | O94: Envoi conseillé : jour 8
A95: 94 | B95: Réseau | C95: BGE Côtes-d’Armor | D95: Bretagne | E95: contact@bge22.fr | F95: Tiers (catalogue BGE Bretagne, 2018) | G95: Simulateurs + check-list | H95: Des outils gratuits pour les créateurs que vous accompagnez | I95: Brouillon prêt | K95: =IF(J95="","",WORKDAY(J95+4,1)) | O95: Envoi conseillé : jour 8
A96: 95 | B96: Réseau | C96: BGE Ille-et-Vilaine | D96: Bretagne | E96: contact@bge35.com | F96: Tiers (catalogue BGE Bretagne, 2018) | G96: Simulateurs + check-list | H96: Des outils gratuits pour les créateurs que vous accompagnez | I96: Brouillon prêt | K96: =IF(J96="","",WORKDAY(J96+4,1)) | O96: Envoi conseillé : jour 8
A97: 96 | B97: Réseau | C97: BGE Morbihan | D97: Bretagne | E97: contact@bge-morbihan.com | F97: Tiers (catalogue BGE Bretagne, 2018) | G97: Simulateurs + check-list | H97: Des outils gratuits pour les créateurs que vous accompagnez | I97: Brouillon prêt | K97: =IF(J97="","",WORKDAY(J97+4,1)) | O97: Envoi conseillé : jour 8
K98: =IF(J98="","",WORKDAY(J98+4,1))
K99: =IF(J99="","",WORKDAY(J99+4,1))
K100: =IF(J100="","",WORKDAY(J100+4,1))
...

Sheet Statistiques
A1: Tableau de bord de la prospection
A3: Contacts avec adresse | B3: =COUNTIF(Suivi!$E$2:$E$200,"*@*") -> 95
A4: Brouillons prêts | B4: =COUNTIF(Suivi!$I$2:$I$200,"Brouillon prêt") -> 31
A5: Envoyés (y compris relancés, répondus, liens) | B5: =COUNTIF(Suivi!$I$2:$I$200,"Envoyé")+COUNTIF(Suivi!$I$2:$I$200,"Relancé")+COUNTIF(Suivi!$I$2:$I$200,"Répondu")+COUNTIF(Suivi!$I$2:$I$200,"Lien obtenu")+COUNTIF(Suivi!$I$2:$I$200,"Refus")+COUNTIF(Suivi!$I$2:$I$200,"Pas de réponse") -> 57
A6: Relancés | B6: =COUNTIF(Suivi!$I$2:$I$200,"Relancé") -> 32
A7: Réponses reçues | B7: =COUNTIF(Suivi!$M$2:$M$200,"Oui") -> 2
A8: Liens obtenus | B8: =COUNTIF(Suivi!$I$2:$I$200,"Lien obtenu") -> 0
A9: Refus | B9: =COUNTIF(Suivi!$I$2:$I$200,"Refus") -> 1
A10: Adresses invalides (rebonds) | B10: =COUNTIF(Suivi!$I$2:$I$200,"Adresse invalide") -> 8
A11: Taux de réponse | B11: =IFERROR(B7/B5,0) -> 0.035087719
A12: Taux d'obtention de lien | B12: =IFERROR(B8/B5,0) -> 0
A13: Relances dues aujourd'hui | B13: =COUNTIFS(Suivi!$K$2:$K$200,"<="&TODAY(),Suivi!$I$2:$I$200,"Envoyé",Suivi!$L$2:$L$200,"") -> 0
A15: Repères habituels : 5 à 15 % de réponses, quelques liens pour 50 envois.
A17: Par catégorie
A18: Catégorie | B18: Contacts | C18: Envoyés | D18: Liens
A19: Média | B19: =COUNTIF(Suivi!$B$2:$B$200,A19) -> 9 | C19: =COUNTIFS(Suivi!$B$2:$B$200,A19,Suivi!$J$2:$J$200,"<>") -> 8 | D19: =COUNTIFS(Suivi!$B$2:$B$200,A19,Suivi!$I$2:$I$200,"Lien obtenu") -> 0
A20: Expert-comptable | B20: =COUNTIF(Suivi!$B$2:$B$200,A20) -> 3 | C20: =COUNTIFS(Suivi!$B$2:$B$200,A20,Suivi!$J$2:$J$200,"<>") -> 1 | D20: =COUNTIFS(Suivi!$B$2:$B$200,A20,Suivi!$I$2:$I$200,"Lien obtenu") -> 0
A21: Fédération | B21: =COUNTIF(Suivi!$B$2:$B$200,A21) -> 5 | C21: =COUNTIFS(Suivi!$B$2:$B$200,A21,Suivi!$J$2:$J$200,"<>") -> 5 | D21: =COUNTIFS(Suivi!$B$2:$B$200,A21,Suivi!$I$2:$I$200,"Lien obtenu") -> 0
A22: CCI | B22: =COUNTIF(Suivi!$B$2:$B$200,A22) -> 18 | C22: =COUNTIFS(Suivi!$B$2:$B$200,A22,Suivi!$J$2:$J$200,"<>") -> 18 | D22: =COUNTIFS(Suivi!$B$2:$B$200,A22,Suivi!$I$2:$I$200,"Lien obtenu") -> 0
A23: CMA | B23: =COUNTIF(Suivi!$B$2:$B$200,A23) -> 20 | C23: =COUNTIFS(Suivi!$B$2:$B$200,A23,Suivi!$J$2:$J$200,"<>") -> 13 | D23: =COUNTIFS(Suivi!$B$2:$B$200,A23,Suivi!$I$2:$I$200,"Lien obtenu") -> 0
A24: Réseau | B24: =COUNTIF(Suivi!$B$2:$B$200,A24) -> 9 | C24: =COUNTIFS(Suivi!$B$2:$B$200,A24,Suivi!$J$2:$J$200,"<>") -> 1 | D24: =COUNTIFS(Suivi!$B$2:$B$200,A24,Suivi!$I$2:$I$200,"Lien obtenu") -> 0
A25: Initiative | B25: =COUNTIF(Suivi!$B$2:$B$200,A25) -> 10 | C25: =COUNTIFS(Suivi!$B$2:$B$200,A25,Suivi!$J$2:$J$200,"<>") -> 3 | D25: =COUNTIFS(Suivi!$B$2:$B$200,A25,Suivi!$I$2:$I$200,"Lien obtenu") -> 0
A26: Réseau Entreprendre | B26: =COUNTIF(Suivi!$B$2:$B$200,A26) -> 8 | C26: =COUNTIFS(Suivi!$B$2:$B$200,A26,Suivi!$J$2:$J$200,"<>") -> 7 | D26: =COUNTIFS(Suivi!$B$2:$B$200,A26,Suivi!$I$2:$I$200,"Lien obtenu") -> 0
A27: Couveuse / CAE | B27: =COUNTIF(Suivi!$B$2:$B$200,A27) -> 11 | C27: =COUNTIFS(Suivi!$B$2:$B$200,A27,Suivi!$J$2:$J$200,"<>") -> 5 | D27: =COUNTIFS(Suivi!$B$2:$B$200,A27,Suivi!$I$2:$I$200,"Lien obtenu") -> 0
A28: Association | B28: =COUNTIF(Suivi!$B$2:$B$200,A28) -> 3 | C28: =COUNTIFS(Suivi!$B$2:$B$200,A28,Suivi!$J$2:$J$200,"<>") -> 3 | D28: =COUNTIFS(Suivi!$B$2:$B$200,A28,Suivi!$I$2:$I$200,"Lien obtenu") -> 0
A29: Total | B29: =SUM(B19:B28) -> 96 | C29: =SUM(C19:C28) -> 64 | D29: =SUM(D19:D28) -> 0

Sheet Mode d'emploi
A1: Mode d'emploi du suivi
A3: Cellules à remplir : les colonnes sur fond jaune clair de l'onglet Suivi (Statut, dates, Réponse, Lien, Notes).
A4: Les brouillons correspondants sont dans Gmail (compte logimalin@gmail.com), dossier Brouillons, avec le même objet.
A6: 1. Le jour de l'envoi : envoie le brouillon, puis passe le Statut à « Envoyé » et saisis la Date d'envoi.
A7: 2. La colonne « Relance prévue » se calcule seule (J+5) et devient orange quand la relance est due.
A8: 3. Relance une seule fois, en deux lignes, puis passe le Statut à « Relancé » et saisis la Date de relance.
A9: 4. À la réponse : Réponse = Oui. Si un lien vers le site est publié, Statut = « Lien obtenu » et colle l'URL.
A10: 5. Mail revenu en erreur : Statut = « Adresse invalide », et cherche la page contact du site.
A12: Règles d'envoi : 10 à 15 mails par jour au maximum, un destinataire par mail (jamais de copie groupée),
A13: une seule relance, et toujours la ligne « répondez STOP » pour se désinscrire.
A14: Fiabilité des adresses : « Tiers » = trouvée dans un annuaire ou un document externe, à vérifier si le mail revient.
A15: Colonne Notes : « Envoi conseillé : jour N » répartit les envois à 13 par jour, adresses officielles d'abord.
A16: Lignes vides en bas de l'onglet Suivi : prêtes pour les nouveaux contacts.
